wavl/__init__.py
wavl-0.0.3.dist-info/METADATA
wavl-0.0.3.dist-info/WHEEL
wavl-0.0.3.dist-info/top_level.txt
wavl-0.0.3.dist-info/RECORD
