Metadata-Version: 2.1
Name: wavl
Version: 0.0.3
Summary: bestest
Home-page: https://wavl.top
Author: synterweyst
License: UNKNOWN
Platform: UNKNOWN
Classifier: Programming Language :: Python :: 3
Classifier: License :: OSI Approved :: MIT License
Classifier: Operating System :: OS Independent
Requires-Python: >=3.6
